{
  "repository": [
    {
      "id": 0
    },
    {
      "id": 1
    },
    {
      "id": 2
    },
    {
      "id": 3
    },
    {
      "id": 4
    },
    {
      "id": 5
    },
    {
      "id": 6,
      "tags": [
        1
      ]
    },
    {
      "id": 7,
      "tags": [
        2
      ]
    },
    {
      "id": 8
    },
    {
      "id": 9,
      "tags": [
        2
      ]
    },
    {
      "id": 10
    },
    {
      "id": 11,
      "tags": [
        1
      ]
    },
    {
      "id": 12
    },
    {
      "id": 13
    }
  ]
}